tests/ucon/__init__.py
tests/ucon/test_algebra.py
tests/ucon/test_core.py
tests/ucon/test_default_graph_conversions.py
tests/ucon/test_dimensionless_units.py
tests/ucon/test_quantity.py
tests/ucon/test_uncertainty.py
tests/ucon/test_units.py
tests/ucon/conversion/__init__.py
tests/ucon/conversion/test_graph.py
tests/ucon/conversion/test_map.py
ucon/__init__.py
ucon/algebra.py
ucon/core.py
ucon/graph.py
ucon/maps.py
ucon/quantity.py
ucon/units.py
ucon-0.5.1.dist-info/licenses/LICENSE
ucon-0.5.1.dist-info/licenses/NOTICE
ucon-0.5.1.dist-info/METADATA
ucon-0.5.1.dist-info/WHEEL
ucon-0.5.1.dist-info/top_level.txt
ucon-0.5.1.dist-info/RECORD
